totp_rs/__init__.py
totp_rs/_lib.cpython-311-aarch64-linux-musl.so
totp_rs/_lib.pyi
totp_rs/py.typed
totp_rs.libs/libgcc_s-2d945d6c.so.1
totp_rs-1.0.0.dist-info/METADATA
totp_rs-1.0.0.dist-info/WHEEL
totp_rs-1.0.0.dist-info/RECORD
totp_rs-1.0.0.dist-info/sboms/auditwheel.cdx.json
